<?xml version="1.0" encoding="utf-8"?>
<Messages>
	<Message prefix="[HLS 200-10]" severity="INFO" keynum="HLS_10_1312" content="Analyzing design file &apos;src/tdt.c&apos; ..." tag=""/>
	<Message prefix="[HLS 200-10]" severity="INFO" keynum="HLS_10_1312" content="Analyzing design file &apos;src/aux.c&apos; ..." tag=""/>
	<Message prefix="[HLS 200-10]" severity="INFO" keynum="HLS_10_1465" content="Validating synthesis directives ..." tag=""/>
	<Message prefix="[HLS 200-111]" severity="INFO" keynum="473" content="Finished Checking Pragmas Time (s): cpu = 00:00:13 ; elapsed = 00:00:09 . Memory (MB): peak = 353.070 ; gain = 0.094 ; free physical = 21283 ; free virtual = 57830" tag=""/>
	<Message prefix="[HLS 200-111]" severity="INFO" keynum="473" content="Finished Linking Time (s): cpu = 00:00:14 ; elapsed = 00:00:10 . Memory (MB): peak = 353.070 ; gain = 0.094 ; free physical = 21282 ; free virtual = 57829" tag=""/>
	<Message prefix="[HLS 200-10]" severity="INFO" keynum="HLS_10_1467" content="Starting code transformations ..." tag=""/>
	<Message prefix="[HLS 200-111]" severity="INFO" keynum="473" content="Finished Standard Transforms Time (s): cpu = 00:00:15 ; elapsed = 00:00:11 . Memory (MB): peak = 353.070 ; gain = 0.094 ; free physical = 21282 ; free virtual = 57829" tag=""/>
	<Message prefix="[HLS 200-10]" severity="INFO" keynum="HLS_10_1472" content="Checking synthesizability ..." tag=""/>
	<Message prefix="[XFORM 203-602]" severity="INFO" keynum="794" content="Inlining function &apos;mod4&apos; into &apos;tdt&apos; (src/tdt.c:177) automatically." tag=""/>
	<Message prefix="[HLS 200-111]" severity="INFO" keynum="473" content="Finished Checking Synthesizability Time (s): cpu = 00:00:15 ; elapsed = 00:00:11 . Memory (MB): peak = 353.070 ; gain = 0.094 ; free physical = 21282 ; free virtual = 57829" tag=""/>
	<Message prefix="[XFORM 203-502]" severity="INFO" keynum="817" content="Unrolling all loops for pipelining in function &apos;tdt&apos; (src/tdt.c:55)." tag=""/>
	<Message prefix="[XFORM 203-501]" severity="INFO" keynum="891" content="Unrolling loop &apos;Loop-1&apos; (src/tdt.c:89) in function &apos;tdt&apos; completely." tag=""/>
	<Message prefix="[XFORM 203-102]" severity="INFO" keynum="696" content="Partitioning array &apos;cs&apos; (src/tdt.c:67) automatically." tag=""/>
	<Message prefix="[XFORM 203-102]" severity="INFO" keynum="696" content="Partitioning array &apos;rs&apos; (src/tdt.c:67) automatically." tag=""/>
	<Message prefix="[XFORM 203-102]" severity="INFO" keynum="696" content="Partitioning array &apos;cd&apos; (src/tdt.c:82) automatically." tag=""/>
	<Message prefix="[XFORM 203-102]" severity="INFO" keynum="696" content="Partitioning array &apos;rd&apos; (src/tdt.c:84) automatically." tag=""/>
	<Message prefix="[XFORM 203-602]" severity="INFO" keynum="794" content="Inlining function &apos;min4&apos; into &apos;tdt&apos; (src/tdt.c:110) automatically." tag=""/>
	<Message prefix="[XFORM 203-602]" severity="INFO" keynum="794" content="Inlining function &apos;max4&apos; into &apos;tdt&apos; (src/tdt.c:118) automatically." tag=""/>
	<Message prefix="[XFORM 203-602]" severity="INFO" keynum="794" content="Inlining function &apos;mod4&apos; into &apos;tdt&apos; (src/tdt.c:177) automatically." tag=""/>
	<Message prefix="[XFORM 203-401]" severity="INFO" keynum="809" content="Performing if-conversion on hyperblock to (src/tdt.c:218:1) in function &apos;tdt&apos;... converting 24 basic blocks." tag=""/>
	<Message prefix="[XFORM 203-11]" severity="INFO" keynum="754" content="Balancing expressions in function &apos;tdt&apos; (src/tdt.c:55)...3 expression(s) balanced." tag=""/>
	<Message prefix="[HLS 200-111]" severity="INFO" keynum="473" content="Finished Pre-synthesis Time (s): cpu = 00:00:16 ; elapsed = 00:00:12 . Memory (MB): peak = 480.977 ; gain = 128.000 ; free physical = 21260 ; free virtual = 57808" tag=""/>
	<Message prefix="[HLS 200-111]" severity="INFO" keynum="473" content="Finished Architecture Synthesis Time (s): cpu = 00:00:17 ; elapsed = 00:00:12 . Memory (MB): peak = 480.977 ; gain = 128.000 ; free physical = 21268 ; free virtual = 57816" tag=""/>
	<Message prefix="[HLS 200-10]" severity="INFO" keynum="HLS_10_1317" content="Starting hardware synthesis ..." tag=""/>
	<Message prefix="[HLS 200-10]" severity="INFO" keynum="HLS_10_1385" content="Synthesizing &apos;tdt&apos; ..." tag=""/>
	<Message prefix="[HLS 200-10]" severity="INFO" keynum="HLS_10_1477" content="----------------------------------------------------------------" tag=""/>
	<Message prefix="[HLS 200-42]" severity="INFO" keynum="HLS_42_1438" content="-- Implementing module &apos;tdt&apos;" tag=""/>
	<Message prefix="[HLS 200-10]" severity="INFO" keynum="HLS_10_1478" content="----------------------------------------------------------------" tag=""/>
	<Message prefix="[SCHED 204-11]" severity="INFO" keynum="139" content="Starting scheduling ..." tag=""/>
	<Message prefix="[SCHED 204-61]" severity="INFO" keynum="112" content="Pipelining function &apos;tdt&apos;." tag=""/>
	<Message prefix="[SCHED 204-61]" severity="INFO" keynum="110" content="Pipelining result : Target II = 1, Final II = 1, Depth = 12." tag=""/>
	<Message prefix="[SCHED 204-11]" severity="INFO" keynum="138" content="Finished scheduling." tag=""/>
	<Message prefix="[HLS 200-111]" severity="INFO" keynum="474" content=" Elapsed time: 12.4 seconds; current allocated memory: 63.013 MB." tag=""/>
	<Message prefix="[BIND 205-100]" severity="INFO" keynum="439" content="Starting micro-architecture generation ..." tag=""/>
	<Message prefix="[BIND 205-101]" severity="INFO" keynum="211" content="Performing variable lifetime analysis." tag=""/>
	<Message prefix="[BIND 205-101]" severity="INFO" keynum="210" content="Exploring resource sharing." tag=""/>
	<Message prefix="[BIND 205-101]" severity="INFO" keynum="206" content="Binding ..." tag=""/>
	<Message prefix="[BIND 205-100]" severity="INFO" keynum="438" content="Finished micro-architecture generation." tag=""/>
	<Message prefix="[HLS 200-111]" severity="INFO" keynum="474" content=" Elapsed time: 0.08 seconds; current allocated memory: 64.018 MB." tag=""/>
	<Message prefix="[HLS 200-10]" severity="INFO" keynum="HLS_10_1483" content="----------------------------------------------------------------" tag=""/>
	<Message prefix="[HLS 200-10]" severity="INFO" keynum="HLS_10_1484" content="-- Generating RTL for module &apos;tdt&apos;" tag=""/>
	<Message prefix="[HLS 200-10]" severity="INFO" keynum="HLS_10_1485" content="----------------------------------------------------------------" tag=""/>
	<Message prefix="[RTGEN 206-500]" severity="INFO" keynum="73" content="Setting interface mode on port &apos;tdt/w_div&apos; to &apos;ap_none&apos;." tag=""/>
	<Message prefix="[RTGEN 206-500]" severity="INFO" keynum="73" content="Setting interface mode on port &apos;tdt/h_div&apos; to &apos;ap_none&apos;." tag=""/>
	<Message prefix="[RTGEN 206-500]" severity="INFO" keynum="73" content="Setting interface mode on port &apos;tdt/d_w&apos; to &apos;ap_none&apos;." tag=""/>
	<Message prefix="[RTGEN 206-500]" severity="INFO" keynum="73" content="Setting interface mode on port &apos;tdt/d_h&apos; to &apos;ap_none&apos;." tag=""/>
	<Message prefix="[RTGEN 206-500]" severity="INFO" keynum="73" content="Setting interface mode on port &apos;tdt/s_w&apos; to &apos;ap_none&apos;." tag=""/>
	<Message prefix="[RTGEN 206-500]" severity="INFO" keynum="73" content="Setting interface mode on port &apos;tdt/s_h&apos; to &apos;ap_none&apos;." tag=""/>
	<Message prefix="[RTGEN 206-500]" severity="INFO" keynum="73" content="Setting interface mode on port &apos;tdt/M0&apos; to &apos;ap_none&apos;." tag=""/>
	<Message prefix="[RTGEN 206-500]" severity="INFO" keynum="73" content="Setting interface mode on port &apos;tdt/M1&apos; to &apos;ap_none&apos;." tag=""/>
	<Message prefix="[RTGEN 206-500]" severity="INFO" keynum="73" content="Setting interface mode on port &apos;tdt/M2&apos; to &apos;ap_none&apos;." tag=""/>
	<Message prefix="[RTGEN 206-500]" severity="INFO" keynum="73" content="Setting interface mode on port &apos;tdt/M3&apos; to &apos;ap_none&apos;." tag=""/>
	<Message prefix="[RTGEN 206-500]" severity="INFO" keynum="73" content="Setting interface mode on port &apos;tdt/M4&apos; to &apos;ap_none&apos;." tag=""/>
	<Message prefix="[RTGEN 206-500]" severity="INFO" keynum="73" content="Setting interface mode on port &apos;tdt/M5&apos; to &apos;ap_none&apos;." tag=""/>
	<Message prefix="[RTGEN 206-500]" severity="INFO" keynum="73" content="Setting interface mode on port &apos;tdt/c&apos; to &apos;ap_none&apos;." tag=""/>
	<Message prefix="[RTGEN 206-500]" severity="INFO" keynum="73" content="Setting interface mode on port &apos;tdt/r&apos; to &apos;ap_none&apos;." tag=""/>
	<Message prefix="[RTGEN 206-500]" severity="INFO" keynum="73" content="Setting interface mode on port &apos;tdt/hs_p&apos; to &apos;ap_vld&apos;." tag=""/>
	<Message prefix="[RTGEN 206-500]" severity="INFO" keynum="73" content="Setting interface mode on port &apos;tdt/hs&apos; to &apos;ap_vld&apos;." tag=""/>
	<Message prefix="[RTGEN 206-500]" severity="INFO" keynum="73" content="Setting interface mode on port &apos;tdt/ws&apos; to &apos;ap_vld&apos;." tag=""/>
	<Message prefix="[RTGEN 206-500]" severity="INFO" keynum="73" content="Setting interface mode on port &apos;tdt/tile_valid&apos; to &apos;ap_vld&apos;." tag=""/>
	<Message prefix="[RTGEN 206-500]" severity="INFO" keynum="73" content="Setting interface mode on port &apos;tdt/left_col&apos; to &apos;ap_vld&apos;." tag=""/>
	<Message prefix="[RTGEN 206-500]" severity="INFO" keynum="73" content="Setting interface mode on port &apos;tdt/top_row&apos; to &apos;ap_vld&apos;." tag=""/>
	<Message prefix="[RTGEN 206-500]" severity="INFO" keynum="73" content="Setting interface mode on port &apos;tdt/baddr&apos; to &apos;ap_vld&apos;." tag=""/>
	<Message prefix="[RTGEN 206-500]" severity="INFO" keynum="73" content="Setting interface mode on port &apos;tdt/cd0&apos; to &apos;ap_vld&apos;." tag=""/>
	<Message prefix="[RTGEN 206-500]" severity="INFO" keynum="73" content="Setting interface mode on port &apos;tdt/cd1&apos; to &apos;ap_vld&apos;." tag=""/>
	<Message prefix="[RTGEN 206-500]" severity="INFO" keynum="73" content="Setting interface mode on port &apos;tdt/cd2&apos; to &apos;ap_vld&apos;." tag=""/>
	<Message prefix="[RTGEN 206-500]" severity="INFO" keynum="73" content="Setting interface mode on port &apos;tdt/cd3&apos; to &apos;ap_vld&apos;." tag=""/>
	<Message prefix="[RTGEN 206-500]" severity="INFO" keynum="73" content="Setting interface mode on port &apos;tdt/mod_db&apos; to &apos;ap_vld&apos;." tag=""/>
	<Message prefix="[RTGEN 206-500]" severity="INFO" keynum="73" content="Setting interface mode on function &apos;tdt&apos; to &apos;ap_ctrl_hs&apos;." tag=""/>
	<Message prefix="[SYN 201-210]" severity="INFO" keynum="402" content="Renamed object name &apos;tdt_mul_27s_13s_32_5_1&apos; to &apos;tdt_mul_27s_13s_3bkb&apos; due to the length limit 20" tag=""/>
	<Message prefix="[SYN 201-210]" severity="INFO" keynum="402" content="Renamed object name &apos;tdt_mac_muladd_13s_12s_12s_25_3_1&apos; to &apos;tdt_mac_muladd_13cud&apos; due to the length limit 20" tag=""/>
	<Message prefix="[RTGEN 206-100]" severity="INFO" keynum="368" content="Generating core module &apos;tdt_mac_muladd_13cud&apos;: 1 instance(s)." tag=""/>
	<Message prefix="[RTGEN 206-100]" severity="INFO" keynum="368" content="Generating core module &apos;tdt_mul_27s_13s_3bkb&apos;: 8 instance(s)." tag=""/>
	<Message prefix="[RTGEN 206-100]" severity="INFO" keynum="369" content="Finished creating RTL model for &apos;tdt&apos;." tag=""/>
	<Message prefix="[HLS 200-111]" severity="INFO" keynum="474" content=" Elapsed time: 0.18 seconds; current allocated memory: 65.871 MB." tag=""/>
	<Message prefix="[RTMG 210-282]" severity="INFO" keynum="RTMG_282_1796" content="Generating pipelined core: &apos;tdt_mul_27s_13s_3bkb_MulnS_0&apos;" tag=""/>
	<Message prefix="[HLS 200-111]" severity="INFO" keynum="473" content="Finished generating all RTL models Time (s): cpu = 00:00:18 ; elapsed = 00:00:14 . Memory (MB): peak = 480.977 ; gain = 128.000 ; free physical = 21248 ; free virtual = 57799" tag=""/>
	<Message prefix="[SYSC 207-301]" severity="INFO" keynum="SYSC_301_1065" content="Generating SystemC RTL for tdt." tag=""/>
	<Message prefix="[VHDL 208-304]" severity="INFO" keynum="VHDL_304_1066" content="Generating VHDL RTL for tdt." tag=""/>
	<Message prefix="[VLOG 209-307]" severity="INFO" keynum="VLOG_307_1067" content="Generating Verilog RTL for tdt." tag=""/>
	<Message prefix="[HLS 200-112]" severity="INFO" keynum="472" content="Total elapsed time: 13.59 seconds; peak allocated memory: 65.871 MB." tag=""/>
</Messages>
